<?xml version="1.0" encoding="utf-8"?>
<openbox_menu xmlns="http://openbox.org/" xmlns:xsi="http://www.w3.org/2001/XMLSchema-instance" xsi:schemaLocation="http://openbox.org/ file:///usr/share/openbox/menu.xsd">
    <menu id="root-menu" label="Openbox 3">
        <item label="Prusaslicer">
            <action name="Execute">
                <execute>/slic3r/slic3r-dist/prusa-slicer --datadir /configs/.config/PrusaSlicer/</execute>
            </action>
        </item>
        <item label="Terminal">
            <action name="Execute">
                <execute>/usr/bin/x-terminal-emulator</execute>
            </action>
        </item>
        <item label="File Explorer">
            <action name="Execute">
                <execute>/usr/bin/pcmanfm</execute>
            </action>
        </item>
        <item label="Htop">
            <action name="Execute">
                <execute>/usr/bin/x-terminal-emulator -e htop</execute>
            </action>
        </item>
    </menu>
</openbox_menu>